Workbook

Sheet Instrucciones
A1: Modelo financiero QJ: Firma de abogados + Josefine Auto
A3: Para qué sirve
A4: Proyecta 24 meses de caja con los dos negocios juntos y te dice en qué mes Josefine Auto puede sostenerte sola (el 'salto').
A5: También incluye un flujo de caja de 13 semanas para controlar la crisis de liquidez semana a semana.
A7: Cómo usarlo
A8: 1. Hoja 'Supuestos': reemplaza los valores de ejemplo por tus números reales. Solo edita las celdas con fondo amarillo y texto azul.
A9: 2. Hoja 'Deudas': escribe cada deuda (saldo, tasa, cuota, meses restantes). Las 3 primeras filas son EJEMPLOS: bórralas o sobrescríbelas.
A10: 3. Hoja 'Supuestos', celda B4: cambia el escenario (Pesimista / Base / Optimista) para ver cómo cambia todo.
A11: 4. Hoja 'Tablero': lee los resultados clave. No se edita.
A12: 5. Hoja 'Flujo 13 semanas': cada lunes llena lo que realmente entró y salió. La semana 1 trae valores de ejemplo.
A14: Código de colores
A15: Texto azul con fondo amarillo = dato que tú cambias. Texto negro = fórmula (no tocar). Texto verde = dato traído de otra hoja.
... A26: La reserva de impuestos es una aproximación. Valida tu situación fiscal (ISR, ITBMS) con tu contador.

Sheet Tablero
A1: Tablero de decisión (no editar: cambia los datos en Supuestos y Deudas)
A3: ESCENARIO
A4: Escenario activo | B4: =Supuestos!$B$4 -> Base
A6: ALERTAS DE CAJA
A7: Mes en que la caja se vuelve negativa | B7: =IFERROR(MATCH(1,'Flujo 24 meses'!$B$43:$Y$43,0),"No ocurre en 24 meses") -> No ocurre en 24 meses
A8: Mes en que la caja cae bajo la reserva mínima | B8: =IFERROR(MATCH(1,'Flujo 24 meses'!$B$42:$Y$42,0),"No ocurre en 24 meses") -> 2
A9: Flujo neto del mes 1 | B9: ='Flujo 24 meses'!B31 -> -2214.5
A10: Ingreso extra necesario en el mes 1 para no perder caja | B10: =MAX(0,-'Flujo 24 meses'!B31) -> 2214.5
A11: Caja más baja en 24 meses | B11: =MIN('Flujo 24 meses'!$B$33:$Y$33) -> 809.20925
A13: DECISIÓN SOBRE JOSEFINE AUTO
A14: Mes en que estás LISTO PARA EL SALTO | B14: =IFERROR(MATCH(1,'Flujo 24 meses'!$B$41:$Y$41,0),"Todavía no en 24 meses") -> 11
A15: Primer mes en que Josefine cubre tus compromisos | B15: =IFERROR(MATCH(1,'Flujo 24 meses'!$B$37:$Y$37,0),"Todavía no en 24 meses") -> 9
A16: Utilidad de Josefine: mes 6 | B16: ='Flujo 24 meses'!G24 -> 2410.7984
A17: Utilidad de Josefine: mes 12 | B17: ='Flujo 24 meses'!M24 -> 4469.4917
A18: Compromisos personales: mes 12 (gastos + cuotas) | B18: ='Flujo 24 meses'!M36 -> 3500
A20: FIRMA DE ABOGADOS
A21: Ingresos de la firma: mes 6 | B21: ='Flujo 24 meses'!G11 -> 3781.5351
A22: Ingresos de la firma: mes 12 | B22: ='Flujo 24 meses'!M11 -> 5400
A23: Igualas activas: mes 12 | B23: ='Flujo 24 meses'!M6 -> 12
A25: CAJA Y DEUDA
A26: Caja al final del mes 6 | B26: ='Flujo 24 meses'!G33 -> 3684.4498
A27: Caja al final del mes 12 | B27: ='Flujo 24 meses'!M33 -> 27681.106
A28: Caja al final del mes 24 | B28: ='Flujo 24 meses'!Y33 -> 97139.767
A29: Deuda total actual | B29: =Deudas!C14 -> 19500
A30: Cuotas mensuales actuales | B30: =Deudas!E14 -> 1000
A31: Intereses mensuales aproximados | B31: =Deudas!H14 -> 254.16667
A33: Prueba los 3 escenarios en Supuestos!B4. Si incluso en Pesimista la caja no se vuelve negativa, el plan es robusto.

Sheet Supuestos
A1: Supuestos (cambia solo las celdas amarillas)
A3: ESCENARIO
A4: Escenario activo | B4: Base | C4: Elige: Pesimista, Base u Optimista
A5: Multiplicador de volumen: Pesimista | B5: 0.6 | C5: Ejemplo: se vende y se capta el 60% de lo esperado
A6: Multiplicador de volumen: Base | B6: 1 | C6: Escenario esperado
A7: Multiplicador de volumen: Optimista | B7: 1.3 | C7: Ejemplo: 30% más de lo esperado
A8: Multiplicador activo | B8: =IF(B4="Pesimista",B5,IF(B4="Optimista",B7,B6)) -> 1 | C8: Se aplica a captación de clientes, carros vendidos y servicios
A10: CAJA Y GASTOS PERSONALES
A11: Ahorros iniciales ($) | B11: 5000 | C11: Dato del usuario: fondo de ahorro actual
A12: Reserva mínima intocable ($) | B12: 2500 | C12: Recomendación del plan: no bajar de aquí
A13: Gastos fijos personales mensuales ($) | B13: 2500 | C13: EJEMPLO: alquiler, comida, servicios, colegios, etc. (sin cuotas de deudas)
A14: Meses de reserva requeridos para el salto | B14: 3 | C14: Condición B del salto
A15: Reserva para impuestos sobre utilidad (%) | B15: 0.1 | C15: EJEMPLO: aproximación; validar con contador
A17: FIRMA DE ABOGADOS (modo 'renta fija', 10-15 h/semana)
A18: Igualas activas al inicio | B18: 0 | C18: EJEMPLO
A19: Igualas nuevas por mes | B19: 1.5 | C19: EJEMPLO: meta de 10 igualas en ~6 meses
A20: Cuota mensual promedio por iguala ($) | B20: 350 | C20: EJEMPLO: referencia $150-600 según paquete
A21: Cancelación mensual de igualas (%) | B21: 0.05 | C21: EJEMPLO: clientes que se van cada mes
A22: Máximo de igualas (capacidad de tiempo) | B22: 12 | C22: EJEMPLO: tope para no quitarle tiempo a Josefine
A23: Sociedades con agente residente al inicio | B23: 0 | C23: EJEMPLO
A24: Nuevas sociedades por mes | B24: 2 | C24: EJEMPLO
A25: Tarifa anual de agente residente ($) | B25: 200 | C25: EJEMPLO: referencia $150-300 al año
A26: Casos puntuales y cobranza: ingreso mensual ($) | B26: 800 | C26: EJEMPLO: trabajos sueltos de precio fijo y cobranza por resultado
A27: Gastos fijos mensuales de la firma ($) | B27: 400 | C27: EJEMPLO: oficina, Colegio, software, teléfono
A29: JOSEFINE AUTO (modelo de bajo capital: consignación + servicios)
A30: Carros vendidos en el mes 1 | B30: 1 | C30: EJEMPLO
A31: Aumento de carros vendidos cada mes | B31: 0.5 | C31: EJEMPLO: +1 carro cada 2 meses
A32: Máximo de carros por mes (capacidad) | B32: 6 | C32: EJEMPLO
A33: Precio promedio de venta por carro ($) | B33: 12000 | C33: EJEMPLO
A34: Comisión por consignación (%) | B34: 0.06 | C34: EJEMPLO: referencia 5-8%
A35: Comisión de financiera / seguro por carro ($) | B35: 150 | C35: EJEMPLO
A36: Costo directo por carro ($) | B36: 150 | C36: EJEMPLO: detailing, fotos, traspaso, pequeñas reparaciones
A37: Servicios (traspasos, inspecciones): ingreso mes 1 ($) | B37: 300 | C37: EJEMPLO
A38: Crecimiento mensual de servicios (%) | B38: 0.08 | C38: EJEMPLO
A39: Gastos fijos mensuales de Josefine ($) | B39: 300 | C39: EJEMPLO
A40: Marketing mensual de Josefine ($) | B40: 250 | C40: EJEMPLO: Marketplace, Instagram, Encuentra24, fotos

Sheet Deudas
A1: Deudas (las filas 4-6 son EJEMPLOS: reemplázalas por tus deudas reales)
A3: Acreedor | B3: Tipo | C3: Saldo ($) | D3: Tasa anual (%) | E3: Cuota mensual ($) | F3: Meses restantes | G3: Prioridad (1 = pagar primero) | H3: Interés mensual aprox. ($)
A4: Banco A (ejemplo) | B4: Préstamo de auto | C4: 9000 | D4: 0.09 | E4: 400 | F4: 24 | G4: 1 | H4: =IF(C4="","",C4*D4/12) -> 67.5
A5: Banco B (ejemplo) | B5: Préstamo personal | C5: 7000 | D5: 0.14 | E5: 350 | F5: 24 | G5: 2 | H5: =IF(C5="","",C5*D5/12) -> 81.666667
A6: Banco C (ejemplo) | B6: Tarjeta de crédito | C6: 3500 | D6: 0.36 | E6: 250 | F6: 18 | G6: 3 | H6: =IF(C6="","",C6*D6/12) -> 105
H7: =IF(C7="","",C7*D7/12)
H8: =IF(C8="","",C8*D8/12)
H9: =IF(C9="","",C9*D9/12)
H10: =IF(C10="","",C10*D10/12)
H11: =IF(C11="","",C11*D11/12)
H12: =IF(C12="","",C12*D12/12)
H13: =IF(C13="","",C13*D13/12)
A14: TOTAL | C14: =SUM(C4:C13) -> 19500 | E14: =SUM(E4:E13) -> 1000 | H14: =SUM(H4:H13) -> 254.16667
A16: Orden de pago sugerido en crisis: 1) deudas con garantía (auto, hipoteca), 2) préstamos personales, 3) tarjetas. Negocia ANTES de atrasarte para proteger tu historial en la APC.
A17: 'Meses restantes' define hasta qué mes del modelo se paga la cuota.

Sheet Flujo 24 meses
A1: Proyección mensual a 24 meses (todo son fórmulas: no editar)
A3: Mes | B3: 1 | C3: 2 | D3: 3 | E3: 4 | F3: 5 | G3: 6 | H3: 7 | I3: 8 | J3: 9 | K3: 10 | L3: 11 | M3: 12 | N3: 13 | O3: 14 | P3: 15 | Q3: 16 | R3: 17 | S3: 18 | T3: 19 | U3: 20 | V3: 21 | W3: 22 | X3: 23 | Y3: 24
A5: FIRMA DE ABOGADOS
A6: Igualas activas (#) | B6: =MIN(Supuestos!$B$22,Supuestos!$B$18*(1-Supuestos!$B$21)+Supuestos!$B$19*Supuestos!$B$8) -> 1.5 | C6: =MIN(Supuestos!$B$22,B6*(1-Supuestos!$B$21)+Supuestos!$B$19*Supuestos!$B$8) -> 2.925 | D6: =MIN(Supuestos!$B$22,C6*(1-Supuestos!$B$21)+Supuestos!$B$19*Supuestos!$B$8) -> 4.27875 | E6: =MIN(Supuestos!$B$22,D6*(1-Supuestos!$B$21)+Supuestos!$B$19*Supuestos!$B$8) -> 5.5648125 | F6: =MIN(Supuestos!$B$22,E6*(1-Supuestos!$B$21)+Supuestos!$B$19*Supuestos!$B$8) -> 6.7865719 | G6: =MIN(Supuestos!$B$22,F6*(1-Supuestos!$B$21)+Supuestos!$B$19*Supuestos!$B$8) -> 7.9472433 | H6: =MIN(Supuestos!$B$22,G6*(1-Supuestos!$B$21)+Supuestos!$B$19*Supuestos!$B$8) -> 9.0498811 | I6: =MIN(Supuestos!$B$22,H6*(1-Supuestos!$B$21)+Supuestos!$B$19*Supuestos!$B$8) -> 10.097387 | J6: =MIN(Supuestos!$B$22,I6*(1-Supuestos!$B$21)+Supuestos!$B$19*Supuestos!$B$8) -> 11.092518 | ... Y6: =MIN(Supuestos!$B$22,X6*(1-Supuestos!$B$21)+Supuestos!$B$19*Supuestos!$B$8) -> 12
A7: Ingreso por igualas | B7: =B6*Supuestos!$B$20 -> 525 | C7: =C6*Supuestos!$B$20 -> 1023.75 | D7: =D6*Supuestos!$B$20 -> 1497.5625 | E7: =E6*Supuestos!$B$20 -> 1947.6844 | F7: =F6*Supuestos!$B$20 -> 2375.3002 | G7: =G6*Supuestos!$B$20 -> 2781.5351 | H7: =H6*Supuestos!$B$20 -> 3167.4584 | I7: =I6*Supuestos!$B$20 -> 3534.0855 | ... Y7: =Y6*Supuestos!$B$20 -> 4200
A8: Sociedades con agente residente (#) | B8: =Supuestos!$B$23+Supuestos!$B$24*Supuestos!$B$8 -> 2 | C8: =B8+Supuestos!$B$24*Supuestos!$B$8 -> 4 | D8: =C8+Supuestos!$B$24*Supuestos!$B$8 -> 6 | E8: =D8+Supuestos!$B$24*Supuestos!$B$8 -> 8 | F8: =E8+Supuestos!$B$24*Supuestos!$B$8 -> 10 | G8: =F8+Supuestos!$B$24*Supuestos!$B$8 -> 12 | H8: =G8+Supuestos!$B$24*Supuestos!$B$8 -> 14 | I8: =H8+Supuestos!$B$24*Supuestos!$B$8 -> 16 | J8: =I8+Supuestos!$B$24*Supuestos!$B$8 -> 18 | ... Y8: =X8+Supuestos!$B$24*Supuestos!$B$8 -> 48
A9: Ingreso agente residente (anual repartido por mes) | B9: =B8*Supuestos!$B$25/12 -> 33.333333 | C9: =C8*Supuestos!$B$25/12 -> 66.666667 | D9: =D8*Supuestos!$B$25/12 -> 100 | E9: =E8*Supuestos!$B$25/12 -> 133.33333 | F9: =F8*Supuestos!$B$25/12 -> 166.66667 | G9: =G8*Supuestos!$B$25/12 -> 200 | H9: =H8*Supuestos!$B$25/12 -> 233.33333 | I9: =I8*Supuestos!$B$25/12 -> 266.66667 | ... Y9: =Y8*Supuestos!$B$25/12 -> 800
A10: Casos puntuales y cobranza | B10: =Supuestos!$B$26*Supuestos!$B$8 -> 800 | C10: =Supuestos!$B$26*Supuestos!$B$8 -> 800 | D10: =Supuestos!$B$26*Supuestos!$B$8 -> 800 | E10: =Supuestos!$B$26*Supuestos!$B$8 -> 800 | F10: =Supuestos!$B$26*Supuestos!$B$8 -> 800 | G10: =Supuestos!$B$26*Supuestos!$B$8 -> 800 | H10: =Supuestos!$B$26*Supuestos!$B$8 -> 800 | I10: =Supuestos!$B$26*Supuestos!$B$8 -> 800 | ... Y10: =Supuestos!$B$26*Supuestos!$B$8 -> 800
A11: Total ingresos de la firma | B11: =B7+B9+B10 -> 1358.3333 | C11: =C7+C9+C10 -> 1890.4167 | D11: =D7+D9+D10 -> 2397.5625 | E11: =E7+E9+E10 -> 2881.0177 | F11: =F7+F9+F10 -> 3341.9668 | G11: =G7+G9+G10 -> 3781.5351 | H11: =H7+H9+H10 -> 4200.7917 | I11: =I7+I9+I10 -> 4600.7521 | ... Y11: =Y7+Y9+Y10 -> 5800
A12: Gastos fijos de la firma | B12: =Supuestos!$B$27 -> 400 | C12: =Supuestos!$B$27 -> 400 | D12: =Supuestos!$B$27 -> 400 | E12: =Supuestos!$B$27 -> 400 | F12: =Supuestos!$B$27 -> 400 | G12: =Supuestos!$B$27 -> 400 | H12: =Supuestos!$B$27 -> 400 | I12: =Supuestos!$B$27 -> 400 | ... Y12: =Supuestos!$B$27 -> 400
A13: Utilidad de la firma | B13: =B11-B12 -> 958.33333 | C13: =C11-C12 -> 1490.4167 | D13: =D11-D12 -> 1997.5625 | E13: =E11-E12 -> 2481.0177 | F13: =F11-F12 -> 2941.9668 | G13: =G11-G12 -> 3381.5351 | H13: =H11-H12 -> 3800.7917 | I13: =I11-I12 -> 4200.7521 | ... Y13: =Y11-Y12 -> 5400
A15: JOSEFINE AUTO
A16: Carros vendidos (#) | B16: =MIN(Supuestos!$B$32,Supuestos!$B$30+Supuestos!$B$31*(B$3-1))*Supuestos!$B$8 -> 1 | C16: =MIN(Supuestos!$B$32,Supuestos!$B$30+Supuestos!$B$31*(C$3-1))*Supuestos!$B$8 -> 1.5 | D16: =MIN(Supuestos!$B$32,Supuestos!$B$30+Supuestos!$B$31*(D$3-1))*Supuestos!$B$8 -> 2 | E16: =MIN(Supuestos!$B$32,Supuestos!$B$30+Supuestos!$B$31*(E$3-1))*Supuestos!$B$8 -> 2.5 | F16: =MIN(Supuestos!$B$32,Supuestos!$B$30+Supuestos!$B$31*(F$3-1))*Supuestos!$B$8 -> 3 | G16: =MIN(Supuestos!$B$32,Supuestos!$B$30+Supuestos!$B$31*(G$3-1))*Supuestos!$B$8 -> 3.5 | H16: =MIN(Supuestos!$B$32,Supuestos!$B$30+Supuestos!$B$31*(H$3-1))*Supuestos!$B$8 -> 4 | I16: =MIN(Supuestos!$B$32,Supuestos!$B$30+Supuestos!$B$31*(I$3-1))*Supuestos!$B$8 -> 4.5 | ... Y16: =MIN(Supuestos!$B$32,Supuestos!$B$30+Supuestos!$B$31*(Y$3-1))*Supuestos!$B$8 -> 6
A17: Comisiones por consignación | B17: =B16*Supuestos!$B$33*Supuestos!$B$34 -> 720 | C17: =C16*Supuestos!$B$33*Supuestos!$B$34 -> 1080 | D17: =D16*Supuestos!$B$33*Supuestos!$B$34 -> 1440 | E17: =E16*Supuestos!$B$33*Supuestos!$B$34 -> 1800 | F17: =F16*Supuestos!$B$33*Supuestos!$B$34 -> 2160 | G17: =G16*Supuestos!$B$33*Supuestos!$B$34 -> 2520 | H17: =H16*Supuestos!$B$33*Supuestos!$B$34 -> 2880 | I17: =I16*Supuestos!$B$33*Supuestos!$B$34 -> 3240 | ... Y17: =Y16*Supuestos!$B$33*Supuestos!$B$34 -> 4320
A18: Comisiones de financiera / seguro | B18: =B16*Supuestos!$B$35 -> 150 | C18: =C16*Supuestos!$B$35 -> 225 | D18: =D16*Supuestos!$B$35 -> 300 | E18: =E16*Supuestos!$B$35 -> 375 | F18: =F16*Supuestos!$B$35 -> 450 | G18: =G16*Supuestos!$B$35 -> 525 | H18: =H16*Supuestos!$B$35 -> 600 | I18: =I16*Supuestos!$B$35 -> 675 | ... Y18: =Y16*Supuestos!$B$35 -> 900
A19: Servicios (traspasos, inspecciones) | B19: =Supuestos!$B$37*Supuestos!$B$8*(1+Supuestos!$B$38)^(B$3-1) -> 300 | C19: =Supuestos!$B$37*Supuestos!$B$8*(1+Supuestos!$B$38)^(C$3-1) -> 324 | D19: =Supuestos!$B$37*Supuestos!$B$8*(1+Supuestos!$B$38)^(D$3-1) -> 349.92 | E19: =Supuestos!$B$37*Supuestos!$B$8*(1+Supuestos!$B$38)^(E$3-1) -> 377.9136 | F19: =Supuestos!$B$37*Supuestos!$B$8*(1+Supuestos!$B$38)^(F$3-1) -> 408.14669 | G19: =Supuestos!$B$37*Supuestos!$B$8*(1+Supuestos!$B$38)^(G$3-1) -> 440.79842 | H19: =Supuestos!$B$37*Supuestos!$B$8*(1+Supuestos!$B$38)^(H$3-1) -> 476.0623 | I19: =Supuestos!$B$37*Supuestos!$B$8*(1+Supuestos!$B$38)^(I$3-1) -> 514.14728 | ... Y19: =Supuestos!$B$37*Supuestos!$B$8*(1+Supuestos!$B$38)^(Y$3-1) -> 1761.4391
A20: Total ingresos de Josefine | B20: =B17+B18+B19 -> 1170 | C20: =C17+C18+C19 -> 1629 | D20: =D17+D18+D19 -> 2089.92 | E20: =E17+E18+E19 -> 2552.9136 | F20: =F17+F18+F19 -> 3018.1467 | G20: =G17+G18+G19 -> 3485.7984 | H20: =H17+H18+H19 -> 3956.0623 | I20: =I17+I18+I19 -> 4429.1473 | ... Y20: =Y17+Y18+Y19 -> 6981.4391
A21: Costos directos por carro | B21: =B16*Supuestos!$B$36 -> 150 | C21: =C16*Supuestos!$B$36 -> 225 | D21: =D16*Supuestos!$B$36 -> 300 | E21: =E16*Supuestos!$B$36 -> 375 | F21: =F16*Supuestos!$B$36 -> 450 | G21: =G16*Supuestos!$B$36 -> 525 | H21: =H16*Supuestos!$B$36 -> 600 | I21: =I16*Supuestos!$B$36 -> 675 | ... Y21: =Y16*Supuestos!$B$36 -> 900
A22: Gastos fijos de Josefine | B22: =Supuestos!$B$39 -> 300 | C22: =Supuestos!$B$39 -> 300 | D22: =Supuestos!$B$39 -> 300 | E22: =Supuestos!$B$39 -> 300 | F22: =Supuestos!$B$39 -> 300 | G22: =Supuestos!$B$39 -> 300 | H22: =Supuestos!$B$39 -> 300 | I22: =Supuestos!$B$39 -> 300 | ... Y22: =Supuestos!$B$39 -> 300
A23: Marketing de Josefine | B23: =Supuestos!$B$40 -> 250 | C23: =Supuestos!$B$40 -> 250 | D23: =Supuestos!$B$40 -> 250 | E23: =Supuestos!$B$40 -> 250 | F23: =Supuestos!$B$40 -> 250 | G23: =Supuestos!$B$40 -> 250 | H23: =Supuestos!$B$40 -> 250 | I23: =Supuestos!$B$40 -> 250 | ... Y23: =Supuestos!$B$40 -> 250
A24: Utilidad de Josefine | B24: =B20-B21-B22-B23 -> 470 | C24: =C20-C21-C22-C23 -> 854 | D24: =D20-D21-D22-D23 -> 1239.92 | E24: =E20-E21-E22-E23 -> 1627.9136 | F24: =F20-F21-F22-F23 -> 2018.1467 | G24: =G20-G21-G22-G23 -> 2410.7984 | H24: =H20-H21-H22-H23 -> 2806.0623 | I24: =I20-I21-I22-I23 -> 3204.1473 | ... Y24: =Y20-Y21-Y22-Y23 -> 5531.4391
A26: CONSOLIDADO Y CAJA
A27: Utilidad de los dos negocios | B27: =B13+B24 -> 1428.3333 | C27: =C13+C24 -> 2344.4167 | D27: =D13+D24 -> 3237.4825 | E27: =E13+E24 -> 4108.9313 | F27: =F13+F24 -> 4960.1135 | G27: =G13+G24 -> 5792.3336 | H27: =H13+H24 -> 6606.854 | I27: =I13+I24 -> 7404.8994 | ... Y27: =Y13+Y24 -> 10931.439
A28: Reserva para impuestos | B28: =MAX(0,B27)*Supuestos!$B$15 -> 142.83333 | C28: =MAX(0,C27)*Supuestos!$B$15 -> 234.44167 | D28: =MAX(0,D27)*Supuestos!$B$15 -> 323.74825 | E28: =MAX(0,E27)*Supuestos!$B$15 -> 410.89313 | F28: =MAX(0,F27)*Supuestos!$B$15 -> 496.01135 | G28: =MAX(0,G27)*Supuestos!$B$15 -> 579.23336 | H28: =MAX(0,H27)*Supuestos!$B$15 -> 660.6854 | I28: =MAX(0,I27)*Supuestos!$B$15 -> 740.48994 | ... Y28: =MAX(0,Y27)*Supuestos!$B$15 -> 1093.1439
A29: Gastos personales | B29: =Supuestos!$B$13 -> 2500 | C29: =Supuestos!$B$13 -> 2500 | D29: =Supuestos!$B$13 -> 2500 | E29: =Supuestos!$B$13 -> 2500 | F29: =Supuestos!$B$13 -> 2500 | G29: =Supuestos!$B$13 -> 2500 | H29: =Supuestos!$B$13 -> 2500 | I29: =Supuestos!$B$13 -> 2500 | ... Y29: =Supuestos!$B$13 -> 2500
A30: Cuotas de deudas | B30: =SUMPRODUCT((Deudas!$F$4:$F$13>=B$3)*Deudas!$E$4:$E$13) -> 1000 | C30: =SUMPRODUCT((Deudas!$F$4:$F$13>=C$3)*Deudas!$E$4:$E$13) -> 1000 | D30: =SUMPRODUCT((Deudas!$F$4:$F$13>=D$3)*Deudas!$E$4:$E$13) -> 1000 | E30: =SUMPRODUCT((Deudas!$F$4:$F$13>=E$3)*Deudas!$E$4:$E$13) -> 1000 | F30: =SUMPRODUCT((Deudas!$F$4:$F$13>=F$3)*Deudas!$E$4:$E$13) -> 1000 | G30: =SUMPRODUCT((Deudas!$F$4:$F$13>=G$3)*Deudas!$E$4:$E$13) -> 1000 | H30: =SUMPRODUCT((Deudas!$F$4:$F$13>=H$3)*Deudas!$E$4:$E$13) -> 1000 | I30: =SUMPRODUCT((Deudas!$F$4:$F$13>=I$3)*Deudas!$E$4:$E$13) -> 1000 | ... Y30: =SUMPRODUCT((Deudas!$F$4:$F$13>=Y$3)*Deudas!$E$4:$E$13) -> 750
A31: Flujo neto del mes | B31: =B27-B28-B29-B30 -> -2214.5 | C31: =C27-C28-C29-C30 -> -1390.025 | D31: =D27-D28-D29-D30 -> -586.26575 | E31: =E27-E28-E29-E30 -> 198.03818 | F31: =F27-F28-F29-F30 -> 964.10216 | G31: =G27-G28-G29-G30 -> 1713.1002 | H31: =H27-H28-H29-H30 -> 2446.1686 | I31: =I27-I28-I29-I30 -> 3164.4095 | ... Y31: =Y27-Y28-Y29-Y30 -> 6588.2952
A32: Caja al inicio del mes | B32: =Supuestos!$B$11 -> 5000 | C32: =B33 -> 2785.5 | D32: =C33 -> 1395.475 | E32: =D33 -> 809.20925 | F32: =E33 -> 1007.2474 | G32: =F33 -> 1971.3496 | H32: =G33 -> 3684.4498 | I32: =H33 -> 6130.6184 | J32: =I33 -> 9295.0279 | ... Y32: =X33 -> 90551.471
A33: Caja al final del mes | B33: =B32+B31 -> 2785.5 | C33: =C32+C31 -> 1395.475 | D33: =D32+D31 -> 809.20925 | E33: =E32+E31 -> 1007.2474 | F33: =F32+F31 -> 1971.3496 | G33: =G32+G31 -> 3684.4498 | H33: =H32+H31 -> 6130.6184 | I33: =I32+I31 -> 9295.0279 | ... Y33: =Y32+Y31 -> 97139.767
A35: SEMÁFOROS DEL SALTO (SÍ / NO)
A36: Compromisos personales (gastos + cuotas) | B36: =B29+B30 -> 3500 | C36: =C29+C30 -> 3500 | D36: =D29+D30 -> 3500 | E36: =E29+E30 -> 3500 | F36: =F29+F30 -> 3500 | G36: =G29+G30 -> 3500 | H36: =H29+H30 -> 3500 | I36: =I29+I30 -> 3500 | ... Y36: =Y29+Y30 -> 3250
A37: Josefine cubre los compromisos este mes | B37: =IF(B24>=B36,1,0) -> 0 | C37: =IF(C24>=C36,1,0) -> 0 | D37: =IF(D24>=D36,1,0) -> 0 | E37: =IF(E24>=E36,1,0) -> 0 | F37: =IF(F24>=F36,1,0) -> 0 | G37: =IF(G24>=G36,1,0) -> 0 | H37: =IF(H24>=H36,1,0) -> 0 | I37: =IF(I24>=I36,1,0) -> 0 | ... Y37: =IF(Y24>=Y36,1,0) -> 1
A38: A. Lo cubre 3 meses seguidos | B38: =0 -> 0 | C38: =0 -> 0 | D38: =IF(SUM(B37:D37)=3,1,0) -> 0 | E38: =IF(SUM(C37:E37)=3,1,0) -> 0 | F38: =IF(SUM(D37:F37)=3,1,0) -> 0 | G38: =IF(SUM(E37:G37)=3,1,0) -> 0 | H38: =IF(SUM(F37:H37)=3,1,0) -> 0 | I38: =IF(SUM(G37:I37)=3,1,0) -> 0 | J38: =IF(SUM(H37:J37)=3,1,0) -> 0 | K38: =IF(SUM(I37:K37)=3,1,0) -> 0 | ... Y38: =IF(SUM(W37:Y37)=3,1,0) -> 1
A39: B. Caja ≥ meses de reserva requeridos | B39: =IF(B33>=Supuestos!$B$14*B36,1,0) -> 0 | C39: =IF(C33>=Supuestos!$B$14*C36,1,0) -> 0 | D39: =IF(D33>=Supuestos!$B$14*D36,1,0) -> 0 | E39: =IF(E33>=Supuestos!$B$14*E36,1,0) -> 0 | F39: =IF(F33>=Supuestos!$B$14*F36,1,0) -> 0 | G39: =IF(G33>=Supuestos!$B$14*G36,1,0) -> 0 | H39: =IF(H33>=Supuestos!$B$14*H36,1,0) -> 0 | I39: =IF(I33>=Supuestos!$B$14*I36,1,0) -> 0 | ... Y39: =IF(Y33>=Supuestos!$B$14*Y36,1,0) -> 1
A40: C. La caja nunca ha sido negativa | B40: =IF(MIN($B33:B33)>=0,1,0) -> 1 | C40: =IF(MIN($B33:C33)>=0,1,0) -> 1 | D40: =IF(MIN($B33:D33)>=0,1,0) -> 1 | E40: =IF(MIN($B33:E33)>=0,1,0) -> 1 | F40: =IF(MIN($B33:F33)>=0,1,0) -> 1 | G40: =IF(MIN($B33:G33)>=0,1,0) -> 1 | H40: =IF(MIN($B33:H33)>=0,1,0) -> 1 | I40: =IF(MIN($B33:I33)>=0,1,0) -> 1 | ... Y40: =IF(MIN($B33:Y33)>=0,1,0) -> 1
A41: LISTO PARA EL SALTO (A + B + C) | B41: =IF(B38+B39+B40=3,1,0) -> 0 | C41: =IF(C38+C39+C40=3,1,0) -> 0 | D41: =IF(D38+D39+D40=3,1,0) -> 0 | E41: =IF(E38+E39+E40=3,1,0) -> 0 | F41: =IF(F38+F39+F40=3,1,0) -> 0 | G41: =IF(G38+G39+G40=3,1,0) -> 0 | H41: =IF(H38+H39+H40=3,1,0) -> 0 | I41: =IF(I38+I39+I40=3,1,0) -> 0 | ... Y41: =IF(Y38+Y39+Y40=3,1,0) -> 1
A42: Alerta: caja bajo la reserva mínima | B42: =IF(B33<Supuestos!$B$12,1,0) -> 0 | C42: =IF(C33<Supuestos!$B$12,1,0) -> 1 | D42: =IF(D33<Supuestos!$B$12,1,0) -> 1 | E42: =IF(E33<Supuestos!$B$12,1,0) -> 1 | F42: =IF(F33<Supuestos!$B$12,1,0) -> 1 | G42: =IF(G33<Supuestos!$B$12,1,0) -> 0 | H42: =IF(H33<Supuestos!$B$12,1,0) -> 0 | I42: =IF(I33<Supuestos!$B$12,1,0) -> 0 | ... Y42: =IF(Y33<Supuestos!$B$12,1,0) -> 0
A43: Alerta: caja negativa | B43: =IF(B33<0,1,0) -> 0 | C43: =IF(C33<0,1,0) -> 0 | D43: =IF(D33<0,1,0) -> 0 | E43: =IF(E33<0,1,0) -> 0 | F43: =IF(F33<0,1,0) -> 0 | G43: =IF(G33<0,1,0) -> 0 | H43: =IF(H33<0,1,0) -> 0 | I43: =IF(I33<0,1,0) -> 0 | ... Y43: =IF(Y33<0,1,0) -> 0

Sheet Flujo 13 semanas
A1: Flujo de caja de 13 semanas (actualízalo cada lunes; la semana 1 trae un EJEMPLO)
A3: Semana | B3: 1 | C3: 2 | D3: 3 | E3: 4 | F3: 5 | G3: 6 | H3: 7 | I3: 8 | J3: 9 | K3: 10 | L3: 11 | M3: 12 | N3: 13
A4: Caja al inicio de la semana | B4: =Supuestos!$B$11 -> 5000 | C4: =B26 -> 4920 | D4: =C26 -> 4920 | E4: =D26 -> 4920 | F4: =E26 -> 4920 | G4: =F26 -> 4920 | H4: =G26 -> 4920 | I4: =H26 -> 4920 | J4: =I26 -> 4920 | ... N4: =M26 -> 4920
A5: ENTRADAS
A6: Cobros de honorarios pendientes | B6: 600
A7: Igualas mensuales | B7: 0
A8: Josefine: comisiones y ventas | B8: 400
A9: Josefine: servicios | B9: 100
A10: Otros ingresos | B10: 0
A11: Total entradas | B11: =SUM(B6:B10) -> 1100 | C11: =SUM(C6:C10) -> 0 | D11: =SUM(D6:D10) -> 0 | E11: =SUM(E6:E10) -> 0 | F11: =SUM(F6:F10) -> 0 | G11: =SUM(G6:G10) -> 0 | H11: =SUM(H6:H10) -> 0 | I11: =SUM(I6:I10) -> 0 | ... N11: =SUM(N6:N10) -> 0
A13: SALIDAS
A14: Cuotas con garantía (auto, hipoteca) | B14: 400
A15: Alquiler / oficina | B15: 0
A16: Planilla / ayudantes | B16: 0
A17: Préstamos personales | B17: 0
A18: Tarjetas de crédito (mínimo o arreglo) | B18: 0
A19: Servicios (luz, agua, internet, teléfono) | B19: 120
A20: Gastos personales y familia | B20: 600
A21: Marketing | B21: 60
A22: Otros gastos | B22: 0
A23: Total salidas | B23: =SUM(B14:B22) -> 1180 | C23: =SUM(C14:C22) -> 0 | D23: =SUM(D14:D22) -> 0 | E23: =SUM(E14:E22) -> 0 | F23: =SUM(F14:F22) -> 0 | G23: =SUM(G14:G22) -> 0 | H23: =SUM(H14:H22) -> 0 | I23: =SUM(I14:I22) -> 0 | ... N23: =SUM(N14:N22) -> 0
A25: Flujo neto de la semana | B25: =B11-B23 -> -80 | C25: =C11-C23 -> 0 | D25: =D11-D23 -> 0 | E25: =E11-E23 -> 0 | F25: =F11-F23 -> 0 | G25: =G11-G23 -> 0 | H25: =H11-H23 -> 0 | I25: =I11-I23 -> 0 | ... N25: =N11-N23 -> 0
A26: Caja al final de la semana | B26: =B4+B25 -> 4920 | C26: =C4+C25 -> 4920 | D26: =D4+D25 -> 4920 | E26: =E4+E25 -> 4920 | F26: =F4+F25 -> 4920 | G26: =G4+G25 -> 4920 | H26: =H4+H25 -> 4920 | I26: =I4+I25 -> 4920 | ... N26: =N4+N25 -> 4920
A27: Alerta | B27: =IF(B26<0,"NEGATIVA",IF(B26<Supuestos!$B$12,"BAJO RESERVA","OK")) -> OK | C27: =IF(C26<0,"NEGATIVA",IF(C26<Supuestos!$B$12,"BAJO RESERVA","OK")) -> OK | D27: =IF(D26<0,"NEGATIVA",IF(D26<Supuestos!$B$12,"BAJO RESERVA","OK")) -> OK | E27: =IF(E26<0,"NEGATIVA",IF(E26<Supuestos!$B$12,"BAJO RESERVA","OK")) -> OK | F27: =IF(F26<0,"NEGATIVA",IF(F26<Supuestos!$B$12,"BAJO RESERVA","OK")) -> OK | G27: =IF(G26<0,"NEGATIVA",IF(G26<Supuestos!$B$12,"BAJO RESERVA","OK")) -> OK | H27: =IF(H26<0,"NEGATIVA",IF(H26<Supuestos!$B$12,"BAJO RESERVA","OK")) -> OK | I27: =IF(I26<0,"NEGATIVA",IF(I26<Supuestos!$B$12,"BAJO RESERVA","OK")) -> OK | ... N27: =IF(N26<0,"NEGATIVA",IF(N26<Supuestos!$B$12,"BAJO RESERVA","OK")) -> OK
A29: Regla: la primera semana que diga NEGATIVA es tu fecha límite real. Negocia con el banco y cobra antes de esa semana.
